filterfx/__init__.py
filterfx/image_enhances.py
filterfx/image_filters.py
filterfx/ocr.py
filterfx/tools.py
filterfx-1.0.0.dist-info/LICENSE
filterfx-1.0.0.dist-info/METADATA
filterfx-1.0.0.dist-info/WHEEL
filterfx-1.0.0.dist-info/top_level.txt
filterfx-1.0.0.dist-info/RECORD
